{
  "quoteSummary": {
    "result": [
      {
        "defaultKeyStatistics": {
          "maxAge": 1,
          "priceHint": {
            "raw": 2,
            "fmt": "2",
            "longFmt": "2"
          },
          "enterpriseValue": {
            "raw": 1354814592,
            "fmt": "1.35B",
            "longFmt": "1,354,814,592"
          },
          "forwardPE": {},
          "profitMargins": {
            "raw": 0.01643,
            "fmt": "1.64%"
          },
          "floatShares": {
            "raw": 66499791,
            "fmt": "66.5M",
            "longFmt": "66,499,791"
          },
          "sharesOutstanding": {
            "raw": 146527008,
            "fmt": "146.53M",
            "longFmt": "146,527,008"
          },
          "sharesShort": {},
          "sharesShortPriorMonth": {},
          "sharesShortPreviousMonthDate": {},
          "dateShortInterest": {},
          "sharesPercentSharesOut": {},
          "heldPercentInsiders": {},
          "heldPercentInstitutions": {},
          "shortRatio": {},
          "shortPercentOfFloat": {},
          "beta": {
            "raw": 0.496931,
            "fmt": "0.5"
          },
          "morningStarOverallRating": {},
          "morningStarRiskRating": {},
          "category": null,
          "bookValue": {
            "raw": 4.136,
            "fmt": "4.14"
          },
          "priceToBook": {
            "raw": 0.5609284,
            "fmt": "0.56"
          },
          "annualReportExpenseRatio": {},
          "ytdReturn": {},
          "beta3Year": {},
          "totalAssets": {},
          "yield": {},
          "fundFamily": null,
          "fundInceptionDate": {},
          "legalType": null,
          "threeYearAverageReturn": {},
          "fiveYearAverageReturn": {},
          "priceToSalesTrailing12Months": {},
          "lastFiscalYearEnd": {
            "raw": 1490918400,
            "fmt": "2017-03-31"
          },
          "nextFiscalYearEnd": {
            "raw": 1553990400,
            "fmt": "2019-03-31"
          },
          "mostRecentQuarter": {
            "raw": 1514678400,
            "fmt": "2017-12-31"
          },
          "earningsQuarterlyGrowth": {
            "raw": 0.402,
            "fmt": "40.20%"
          },
          "revenueQuarterlyGrowth": {},
          "netIncomeToCommon": {
            "raw": 37692612,
            "fmt": "37.69M",
            "longFmt": "37,692,612"
          },
          "trailingEps": {
            "raw": 0.257,
            "fmt": "0.26"
          },
          "forwardEps": {},
          "pegRatio": {},
          "lastSplitFactor": "10/1",
          "lastSplitDate": {
            "raw": 1456358400,
            "fmt": "2016-02-25"
          },
          "enterpriseToRevenue": {
            "raw": 0.591,
            "fmt": "0.59"
          },
          "enterpriseToEbitda": {
            "raw": 10.477,
            "fmt": "10.48"
          },
          "52WeekChange": {
            "raw": "Infinity",
            "fmt": "\u00e2\u02c6\u017e%"
          },
          "SandP52WeekChange": {
            "raw": 0.17201865,
            "fmt": "17.20%"
          },
          "lastDividendValue": {},
          "lastCapGain": {},
          "annualHoldingsTurnover": {}
        },
        "summaryProfile": {
          "address1": "Bhandari House",
          "address2": "Village Meharban Rahon Road",
          "city": "Ludhiana",
          "zip": "141007",
          "country": "India",
          "phone": "91 88 7201 6410",
          "fax": "91 16 1269 0394",
          "website": "http://www.bhandariexport.com",
          "industry": "Textile - Apparel Clothing",
          "sector": "Consumer Goods",
          "longBusinessSummary": "Bhandari Hosiery Exports Limited manufactures garment for men, women, and kids in India. It manufactures, processes, and trades in dyed and undyed fabrics; and manufactures and exports knitted hosiery garments, such as T- shirts, pull overs, sweat shirts, bermudas, pollo shirts, track suits, payajamas, lowers, ladies knitted tops with embroidery and prints, etc. The company also exports its products to approximately 18 countries, including the United States, Canada, the United Kingdom, and the European Union. Bhandari Hosiery Exports Limited was founded in 1993 and is based in Ludhiana, India.",
          "fullTimeEmployees": 286,
          "companyOfficers": [],
          "maxAge": 86400
        },
        "financialData": {
          "maxAge": 86400,
          "currentPrice": {
            "raw": 2.32,
            "fmt": "2.32"
          },
          "targetHighPrice": {},
          "targetLowPrice": {},
          "targetMeanPrice": {},
          "targetMedianPrice": {},
          "recommendationMean": {},
          "recommendationKey": "none",
          "numberOfAnalystOpinions": {},
          "totalCash": {
            "raw": 11885516,
            "fmt": "11.89M",
            "longFmt": "11,885,516"
          },
          "totalCashPerShare": {
            "raw": 0.081,
            "fmt": "0.08"
          },
          "ebitda": {
            "raw": 129316720,
            "fmt": "129.32M",
            "longFmt": "129,316,720"
          },
          "totalDebt": {
            "raw": 867043264,
            "fmt": "867.04M",
            "longFmt": "867,043,264"
          },
          "quickRatio": {},
          "currentRatio": {},
          "totalRevenue": {
            "raw": 2294079232,
            "fmt": "2.29B",
            "longFmt": "2,294,079,232"
          },
          "debtToEquity": {
            "raw": 143.06,
            "fmt": "143.06"
          },
          "revenuePerShare": {
            "raw": 15.656,
            "fmt": "15.66"
          },
          "returnOnAssets": {},
          "returnOnEquity": {},
          "grossProfits": {
            "raw": 354909780,
            "fmt": "354.91M",
            "longFmt": "354,909,780"
          },
          "freeCashflow": {},
          "operatingCashflow": {},
          "earningsGrowth": {
            "raw": 0.402,
            "fmt": "40.20%"
          },
          "revenueGrowth": {
            "raw": 0.235,
            "fmt": "23.50%"
          },
          "grossMargins": {
            "raw": 0.168,
            "fmt": "16.80%"
          },
          "ebitdaMargins": {
            "raw": 0.05637,
            "fmt": "5.64%"
          },
          "operatingMargins": {
            "raw": 0.042859998,
            "fmt": "4.29%"
          },
          "profitMargins": {
            "raw": 0.01643,
            "fmt": "1.64%"
          },
          "financialCurrency": "INR"
        }
      }
    ],
    "error": null
  }
}