{
  "quoteSummary": {
    "result": [
      {
        "defaultKeyStatistics": {
          "maxAge": 1,
          "priceHint": {
            "raw": 2,
            "fmt": "2",
            "longFmt": "2"
          },
          "enterpriseValue": {
            "raw": 329332160,
            "fmt": "329.33M",
            "longFmt": "329,332,160"
          },
          "forwardPE": {},
          "profitMargins": {
            "raw": 0.031059999,
            "fmt": "3.11%"
          },
          "floatShares": {
            "raw": 4743072,
            "fmt": "4.74M",
            "longFmt": "4,743,072"
          },
          "sharesOutstanding": {
            "raw": 12470000,
            "fmt": "12.47M",
            "longFmt": "12,470,000"
          },
          "sharesShort": {},
          "sharesShortPriorMonth": {},
          "sharesShortPreviousMonthDate": {},
          "dateShortInterest": {},
          "sharesPercentSharesOut": {},
          "heldPercentInsiders": {},
          "heldPercentInstitutions": {},
          "shortRatio": {},
          "shortPercentOfFloat": {},
          "beta": {
            "raw": 1.327086,
            "fmt": "1.33"
          },
          "morningStarOverallRating": {},
          "morningStarRiskRating": {},
          "category": null,
          "bookValue": {
            "raw": 71.444,
            "fmt": "71.44"
          },
          "priceToBook": {
            "raw": 0.21835284,
            "fmt": "0.22"
          },
          "annualReportExpenseRatio": {},
          "ytdReturn": {},
          "beta3Year": {},
          "totalAssets": {},
          "yield": {},
          "fundFamily": null,
          "fundInceptionDate": {},
          "legalType": null,
          "threeYearAverageReturn": {},
          "fiveYearAverageReturn": {},
          "priceToSalesTrailing12Months": {},
          "lastFiscalYearEnd": {
            "raw": 1490918400,
            "fmt": "2017-03-31"
          },
          "nextFiscalYearEnd": {
            "raw": 1553990400,
            "fmt": "2019-03-31"
          },
          "mostRecentQuarter": {
            "raw": 1364688000,
            "fmt": "2013-03-31"
          },
          "earningsQuarterlyGrowth": {},
          "revenueQuarterlyGrowth": {},
          "netIncomeToCommon": {
            "raw": 13679158,
            "fmt": "13.68M",
            "longFmt": "13,679,158"
          },
          "trailingEps": {
            "raw": 1.097,
            "fmt": "1.10"
          },
          "forwardEps": {},
          "pegRatio": {},
          "lastSplitFactor": "4/1",
          "lastSplitDate": {
            "raw": 1363651200,
            "fmt": "2013-03-19"
          },
          "enterpriseToRevenue": {
            "raw": 0.748,
            "fmt": "0.75"
          },
          "enterpriseToEbitda": {
            "raw": 21.37,
            "fmt": "21.37"
          },
          "52WeekChange": {
            "raw": -0.29094827,
            "fmt": "-29.09%"
          },
          "SandP52WeekChange": {
            "raw": 0.17201865,
            "fmt": "17.20%"
          },
          "lastDividendValue": {},
          "lastCapGain": {},
          "annualHoldingsTurnover": {}
        },
        "summaryProfile": {
          "address1": "201, Pushpratna Paradise",
          "address2": "9/5, New Palasia",
          "city": "Indore",
          "zip": "452001",
          "country": "India",
          "phone": "91 73 1404 1435",
          "fax": "91 73 1404 1435",
          "website": "http://www.medicaps.com",
          "industry": "Drugs - Generic",
          "sector": "Healthcare",
          "longBusinessSummary": "Medi-Caps Limited manufactures, distributes, and sells empty hard gelatin capsule shells in India. It offers halal gelatin, liquid fill, SLS free, flavored, and preservative free capsules. The company was incorporated in 1983 and is based in Indore, India.",
          "companyOfficers": [],
          "maxAge": 86400
        },
        "financialData": {
          "maxAge": 86400,
          "currentPrice": {
            "raw": 15.6,
            "fmt": "15.60"
          },
          "targetHighPrice": {},
          "targetLowPrice": {},
          "targetMeanPrice": {},
          "targetMedianPrice": {},
          "recommendationMean": {},
          "recommendationKey": "none",
          "numberOfAnalystOpinions": {},
          "totalCash": {
            "raw": 22059106,
            "fmt": "22.06M",
            "longFmt": "22,059,106"
          },
          "totalCashPerShare": {
            "raw": 1.769,
            "fmt": "1.77"
          },
          "ebitda": {
            "raw": 15410689,
            "fmt": "15.41M",
            "longFmt": "15,410,689"
          },
          "totalDebt": {
            "raw": 62711768,
            "fmt": "62.71M",
            "longFmt": "62,711,768"
          },
          "quickRatio": {
            "raw": 2.587,
            "fmt": "2.59"
          },
          "currentRatio": {
            "raw": 4.892,
            "fmt": "4.89"
          },
          "totalRevenue": {
            "raw": 440381600,
            "fmt": "440.38M",
            "longFmt": "440,381,600"
          },
          "debtToEquity": {
            "raw": 6.918,
            "fmt": "6.92"
          },
          "revenuePerShare": {
            "raw": 35.315,
            "fmt": "35.31"
          },
          "returnOnAssets": {
            "raw": -0.00176,
            "fmt": "-0.18%"
          },
          "returnOnEquity": {
            "raw": 0.01597,
            "fmt": "1.60%"
          },
          "grossProfits": {
            "raw": 213957023,
            "fmt": "213.96M",
            "longFmt": "213,957,023"
          },
          "freeCashflow": {
            "raw": 13142485,
            "fmt": "13.14M",
            "longFmt": "13,142,485"
          },
          "operatingCashflow": {
            "raw": 40193252,
            "fmt": "40.19M",
            "longFmt": "40,193,252"
          },
          "earningsGrowth": {},
          "revenueGrowth": {
            "raw": 0.406,
            "fmt": "40.60%"
          },
          "grossMargins": {
            "raw": 0.48584,
            "fmt": "48.58%"
          },
          "ebitdaMargins": {
            "raw": 0.03499,
            "fmt": "3.50%"
          },
          "operatingMargins": {
            "raw": -0.0060799997,
            "fmt": "-0.61%"
          },
          "profitMargins": {
            "raw": 0.031059999,
            "fmt": "3.11%"
          },
          "financialCurrency": "INR"
        }
      }
    ],
    "error": null
  }
}