
 [
{
"symbol" : "526525",
"exchange" : "BOM",
"id": "5728943",
"t" : "526525",
"e" : "BOM",
"name" : "WORLDWIDE LEATHER EXPORTS LTD."
, "f_reuters_url" : "http:\u002F\u002Fstocks.us.reuters.com\u002Fstocks\u002Fratios.asp?rpc=66\u0026symbol=",
"f_recent_quarter_date" : "",
"f_annual_date" : "",
"f_ttm_date" : "",
"financials" :
[{
"f_type" : "Income\u0026nbsp\u003BStatement"
,"url" : "http:www.google.comfinance?fstype=ii&q=BOM:526525"
,"f_figures" :
[
]
},
{
"f_type" : "Balance\u0026nbsp\u003BSheet"
,"url" : "http:www.google.comfinance?fstype=bi&q=BOM:526525"
,"f_figures" :
[
]
},
{
"f_type" : "Cash\u0026nbsp\u003BFlow"
,"url" : "http:www.google.comfinance?fstype=ci&q=BOM:526525"
,"f_figures" :
[
]
}],
"kr_recent_quarter_date" : "",
"kr_annual_date" : "",
"kr_ttm_date" : "TTM",
"keyratios" :
[
]
, "c" : "-0.32",
"l" : "6.11",
"cp" : "-4.98",
"ccol" : "chr",
"op" : "6.11",
"hi" : "6.11",
"lo" : "6.11",
"vo" : "100.00",
"avvo" : "",
"hi52" : "8.37",
"lo52" : "5.70",
"mc" : "",
"pe" : "",
"fwpe" : "",
"beta" : "",
"eps" : "",
"dy" : "",
"ldiv" : "",
"shares" : "",
"instown" : "",
"eo":""
, "related" : [
{
"id" : "5728943",
"name" : "WORLDWIDE LEATHER EXPORTS LTD.",
"t" : "526525",
"e" : "BOM",
"l" : "6.11",
"c" : "-0.32",
"mc" : "",
"cp" : "-4.98",
"ccol" : "chr"
}
,
{
"id" : "6782773",
"name" : "ANKA INDIA LTD.",
"t" : "531673",
"e" : "BOM",
"l" : "18.60",
"c" : "0.00",
"mc" : "",
"cp" : "0.00",
"ccol" : "chb"
}
,
{
"id" : "8072874",
"name" : "NB FOOTWEAR LTD.",
"t" : "523242",
"e" : "BOM",
"l" : "6.30",
"c" : "+0.30",
"mc" : "",
"cp" : "5.00",
"ccol" : "chg"
}
,
{
"id" : "10990149",
"name" : "LAKHANI INDIA LTD.",
"t" : "531085",
"e" : "BOM",
"l" : "0.00",
"c" : "-34.80",
"mc" : "",
"cp" : "-100.00",
"ccol" : "chr"
}
,
{
"id" : "12992411",
"name" : "S.R.INDUSTRIES LTD.",
"t" : "513515",
"e" : "BOM",
"l" : "32.70",
"c" : "+0.20",
"mc" : "",
"cp" : "0.62",
"ccol" : "chg"
}
,
{
"id" : "1049398",
"name" : "HIGH STREET FILATEX LTD.",
"t" : "531301",
"e" : "BOM",
"l" : "9.88",
"c" : "0.00",
"mc" : "",
"cp" : "0.00",
"ccol" : "chb"
}
,
{
"id" : "11951200",
"name" : "EURO LEDER FASHION LTD.",
"t" : "526468",
"e" : "BOM",
"l" : "20.00",
"c" : "0.00",
"mc" : "",
"cp" : "0.00",
"ccol" : "chb"
}
,
{
"id" : "10392308",
"name" : "INTEGRAL KNIT CO.LTD.",
"t" : "514298",
"e" : "BOM",
"l" : "0.00",
"c" : "-7.66",
"mc" : "",
"cp" : "-100.00",
"ccol" : "chr"
}
,
{
"id" : "8252419",
"name" : "SPICE ISLANDS APPARELS LTD.",
"t" : "526827",
"e" : "BOM",
"l" : "24.50",
"c" : "-0.05",
"mc" : "",
"cp" : "-0.20",
"ccol" : "chr"
}
,
{
"id" : "16080678",
"name" : "TATIA GLOBAL VENNTURE LTD.",
"t" : "521228",
"e" : "BOM",
"l" : "0.54",
"c" : "0.00",
"mc" : "",
"cp" : "0.00",
"ccol" : "chb"
}
,
{
"id" : "2795540",
"name" : "CEENIK EXPORTS (INDIA) LTD.",
"t" : "531119",
"e" : "BOM",
"l" : "8.25",
"c" : "0.00",
"mc" : "",
"cp" : "0.00",
"ccol" : "chb"
}
]
,"moreresources" : [
]
}]
